audio_journal/__init__.py
audio_journal/_modidx.py
audio_journal/config.py
audio_journal/gpt.py
audio_journal/main.py
audio_journal/notify.py
audio_journal/notion.py
audio_journal/record.py
audio_journal/sounds.py
audio_journal/transcribe.py
audio_journal/beeps/error.wav
audio_journal/beeps/start.wav
audio_journal/beeps/stop.wav
audio_journal/beeps/success.wav
audio_journal-0.1.0.dist-info/LICENSE
audio_journal-0.1.0.dist-info/METADATA
audio_journal-0.1.0.dist-info/WHEEL
audio_journal-0.1.0.dist-info/entry_points.txt
audio_journal-0.1.0.dist-info/top_level.txt
audio_journal-0.1.0.dist-info/RECORD
