Metadata-Version: 2.1
Name: audio-journal
Version: 0.1.0
Summary: CLI tool to transcribe audio and store it in Notion
Home-page: https://github.com/smith-kyle/audio-journal
Author: Kyle Smith
Author-email: kyle@gitnotebooks.com
License: Apache Software License 2.0
Keywords: nbdev jupyter notebook python
Platform: UNKNOWN
Classifier: Development Status :: 4 - Beta
Classifier: Intended Audience :: Developers
Classifier: Natural Language :: English
Classifier: Programming Language :: Python :: 3.7
Classifier: Programming Language :: Python :: 3.8
Classifier: Programming Language :: Python :: 3.9
Classifier: Programming Language :: Python :: 3.10
Classifier: License :: OSI Approved :: Apache Software License
Requires-Python: >=3.7
License-File: LICENSE
Requires-Dist: sounddevice
Requires-Dist: notion-client
Requires-Dist: openai-whisper
Requires-Dist: load-dotenv
Requires-Dist: soundfile
Requires-Dist: pydub
Requires-Dist: openai
Provides-Extra: dev
